[{"analysis_url": "https://api.spotify.com/v1/audio-analysis/6PGoSes0D9eUDeeAafB2As", "duration_ms": 213400, "speechiness": 0.103, "energy": 0.582, "loudness": -7.38, "track_href": "https://api.spotify.com/v1/tracks/6PGoSes0D9eUDeeAafB2As", "id": "6PGoSes0D9eUDeeAafB2As", "time_signature": 4, "mode": 1, "danceability": 0.798, "uri": "spotify:track:6PGoSes0D9eUDeeAafB2As", "valence": 0.766, "instrumentalness": 0, "liveness": 0.153, "tempo": 126.075, "key": 10, "type": "audio_features", "acousticness": 0.29}, {"analysis_url": "https://api.spotify.com/v1/audio-analysis/6eT7xZZlB2mwyzJ2sUKG6w", "duration_ms": 256533, "speechiness": 0.0349, "energy": 0.568, "loudness": -7.678, "track_href": "https://api.spotify.com/v1/tracks/6eT7xZZlB2mwyzJ2sUKG6w", "id": "6eT7xZZlB2mwyzJ2sUKG6w", "time_signature": 4, "mode": 1, "danceability": 0.674, "uri": "spotify:track:6eT7xZZlB2mwyzJ2sUKG6w", "valence": 0.321, "instrumentalness": 0, "liveness": 0.0863, "tempo": 130.081, "key": 7, "type": "audio_features", "acousticness": 0.216}, {"analysis_url": "https://api.spotify.com/v1/audio-analysis/0q75NwOoFiARAVp4EXU4Bs", "duration_ms": 275080, "speechiness": 0.0747, "energy": 0.594, "loudness": -6.2, "track_href": "https://api.spotify.com/v1/tracks/0q75NwOoFiARAVp4EXU4Bs", "id": "0q75NwOoFiARAVp4EXU4Bs", "time_signature": 4, "mode": 1, "danceability": 0.795, "uri": "spotify:track:0q75NwOoFiARAVp4EXU4Bs", "valence": 0.409, "instrumentalness": 0, "liveness": 0.162, "tempo": 135.002, "key": 0, "type": "audio_features", "acousticness": 0.111}, {"analysis_url": "https://api.spotify.com/v1/audio-analysis/1WIZiOuNO3woKfdlSK2gNn", "duration_ms": 169345, "speechiness": 0.0726, "energy": 0.66, "loudness": -4.86, "track_href": "https://api.spotify.com/v1/tracks/1WIZiOuNO3woKfdlSK2gNn", "id": "1WIZiOuNO3woKfdlSK2gNn", "time_signature": 4, "mode": 0, "danceability": 0.804, "uri": "spotify:track:1WIZiOuNO3woKfdlSK2gNn", "valence": 0.257, "instrumentalness": 0, "liveness": 0.103, "tempo": 94.053, "key": 10, "type": "audio_features", "acousticness": 0.0319}, {"analysis_url": "https://api.spotify.com/v1/audio-analysis/6HZILIRieu8S0iqY8kIKhj", "duration_ms": 185947, "speechiness": 0.365, "energy": 0.514, "loudness": -6.763, "track_href": "https://api.spotify.com/v1/tracks/6HZILIRieu8S0iqY8kIKhj", "id": "6HZILIRieu8S0iqY8kIKhj", "time_signature": 4, "mode": 1, "danceability": 0.637, "uri": "spotify:track:6HZILIRieu8S0iqY8kIKhj", "valence": 0.402, "instrumentalness": 0, "liveness": 0.094, "tempo": 139.931, "key": 1, "type": "audio_features", "acousticness": 0.0047}, {"analysis_url": "https://api.spotify.com/v1/audio-analysis/3kxfsdsCpFgN412fpnW85Y", "duration_ms": 326933, "speechiness": 0.0794, "energy": 0.359, "loudness": -10.401, "track_href": "https://api.spotify.com/v1/tracks/3kxfsdsCpFgN412fpnW85Y", "id": "3kxfsdsCpFgN412fpnW85Y", "time_signature": 4, "mode": 1, "danceability": 0.743, "uri": "spotify:track:3kxfsdsCpFgN412fpnW85Y", "valence": 0.587, "instrumentalness": 0.00611, "liveness": 0.137, "tempo": 160.083, "key": 1, "type": "audio_features", "acousticness": 0.199}, {"analysis_url": "https://api.spotify.com/v1/audio-analysis/2ANLarE8yHVsLWW21nj79M", "duration_ms": 163944, "speechiness": 0.461, "energy": 0.359, "loudness": -7.417, "track_href": "https://api.spotify.com/v1/tracks/2ANLarE8yHVsLWW21nj79M", "id": "2ANLarE8yHVsLWW21nj79M", "time_signature": 4, "mode": 1, "danceability": 0.843, "uri": "spotify:track:2ANLarE8yHVsLWW21nj79M", "valence": 0.156, "instrumentalness": 0, "liveness": 0.12, "tempo": 81.987, "key": 0, "type": "audio_features", "acousticness": 0.069}, {"analysis_url": "https://api.spotify.com/v1/audio-analysis/2ZdCrBA52bb4pIG3tOOZiQ", "duration_ms": 173419, "speechiness": 0.172, "energy": 0.606, "loudness": -5.286, "track_href": "https://api.spotify.com/v1/tracks/2ZdCrBA52bb4pIG3tOOZiQ", "id": "2ZdCrBA52bb4pIG3tOOZiQ", "time_signature": 4, "mode": 1, "danceability": 0.747, "uri": "spotify:track:2ZdCrBA52bb4pIG3tOOZiQ", "valence": 0.2, "instrumentalness": 0, "liveness": 0.281, "tempo": 155.055, "key": 4, "type": "audio_features", "acousticness": 0.222}, {"analysis_url": "https://api.spotify.com/v1/audio-analysis/1e1JKLEDKP7hEQzJfNAgPl", "duration_ms": 181812, "speechiness": 0.29, "energy": 0.586, "loudness": -7.372, "track_href": "https://api.spotify.com/v1/tracks/1e1JKLEDKP7hEQzJfNAgPl", "id": "1e1JKLEDKP7hEQzJfNAgPl", "time_signature": 4, "mode": 0, "danceability": 0.791, "uri": "spotify:track:1e1JKLEDKP7hEQzJfNAgPl", "valence": 0.413, "instrumentalness": 0, "liveness": 0.46, "tempo": 163.029, "key": 11, "type": "audio_features", "acousticness": 0.012}, {"analysis_url": "https://api.spotify.com/v1/audio-analysis/6c7D34787LOtPm8tzhsLgH", "duration_ms": 276333, "speechiness": 0.344, "energy": 0.444, "loudness": -8.126, "track_href": "https://api.spotify.com/v1/tracks/6c7D34787LOtPm8tzhsLgH", "id": "6c7D34787LOtPm8tzhsLgH", "time_signature": 4, "mode": 0, "danceability": 0.91, "uri": "spotify:track:6c7D34787LOtPm8tzhsLgH", "valence": 0.53, "instrumentalness": 0, "liveness": 0.137, "tempo": 149.953, "key": 1, "type": "audio_features", "acousticness": 0.022}, {"analysis_url": "https://api.spotify.com/v1/audio-analysis/1QgTBfRN5m81a5K01qens6", "duration_ms": 247347, "speechiness": 0.269, "energy": 0.513, "loudness": -6.568, "track_href": "https://api.spotify.com/v1/tracks/1QgTBfRN5m81a5K01qens6", "id": "1QgTBfRN5m81a5K01qens6", "time_signature": 4, "mode": 0, "danceability": 0.791, "uri": "spotify:track:1QgTBfRN5m81a5K01qens6", "valence": 0.481, "instrumentalness": 2.83e-05, "liveness": 0.101, "tempo": 76.997, "key": 10, "type": "audio_features", "acousticness": 0.0235}, {"analysis_url": "https://api.spotify.com/v1/audio-analysis/25oOaleife6E2MIKmFkPvg", "duration_ms": 215307, "speechiness": 0.0627, "energy": 0.597, "loudness": -6.336, "track_href": "https://api.spotify.com/v1/tracks/25oOaleife6E2MIKmFkPvg", "id": "25oOaleife6E2MIKmFkPvg", "time_signature": 4, "mode": 1, "danceability": 0.842, "uri": "spotify:track:25oOaleife6E2MIKmFkPvg", "valence": 0.298, "instrumentalness": 0, "liveness": 0.124, "tempo": 145.992, "key": 2, "type": "audio_features", "acousticness": 0.00252}, {"analysis_url": "https://api.spotify.com/v1/audio-analysis/6H0AwSQ20mo62jGlPGB8S6", "duration_ms": 210200, "speechiness": 0.118, "energy": 0.516, "loudness": -7.461, "track_href": "https://api.spotify.com/v1/tracks/6H0AwSQ20mo62jGlPGB8S6", "id": "6H0AwSQ20mo62jGlPGB8S6", "time_signature": 4, "mode": 0, "danceability": 0.841, "uri": "spotify:track:6H0AwSQ20mo62jGlPGB8S6", "valence": 0.556, "instrumentalness": 0.00072, "liveness": 0.111, "tempo": 145.995, "key": 11, "type": "audio_features", "acousticness": 0.0263}, {"analysis_url": "https://api.spotify.com/v1/audio-analysis/1HTtUBEY3tuw2btgwwI2Ja", "duration_ms": 233087, "speechiness": 0.168, "energy": 0.633, "loudness": -5.475, "track_href": "https://api.spotify.com/v1/tracks/1HTtUBEY3tuw2btgwwI2Ja", "id": "1HTtUBEY3tuw2btgwwI2Ja", "time_signature": 4, "mode": 1, "danceability": 0.89, "uri": "spotify:track:1HTtUBEY3tuw2btgwwI2Ja", "valence": 0.425, "instrumentalness": 0.000343, "liveness": 0.0993, "tempo": 139.948, "key": 11, "type": "audio_features", "acousticness": 0.0232}, {"analysis_url": "https://api.spotify.com/v1/audio-analysis/1MJErNPIQUoEMu4YUUmecm", "duration_ms": 258789, "speechiness": 0.112, "energy": 0.563, "loudness": -6.635, "track_href": "https://api.spotify.com/v1/tracks/1MJErNPIQUoEMu4YUUmecm", "id": "1MJErNPIQUoEMu4YUUmecm", "time_signature": 4, "mode": 0, "danceability": 0.859, "uri": "spotify:track:1MJErNPIQUoEMu4YUUmecm", "valence": 0.412, "instrumentalness": 0, "liveness": 0.0685, "tempo": 119.934, "key": 1, "type": "audio_features", "acousticness": 0.0541}, {"analysis_url": "https://api.spotify.com/v1/audio-analysis/4wdZdkEugVVorAfzqRqC6N", "duration_ms": 229053, "speechiness": 0.158, "energy": 0.684, "loudness": -5.468, "track_href": "https://api.spotify.com/v1/tracks/4wdZdkEugVVorAfzqRqC6N", "id": "4wdZdkEugVVorAfzqRqC6N", "time_signature": 4, "mode": 1, "danceability": 0.672, "uri": "spotify:track:4wdZdkEugVVorAfzqRqC6N", "valence": 0.428, "instrumentalness": 0, "liveness": 0.081, "tempo": 180.008, "key": 4, "type": "audio_features", "acousticness": 0.604}, {"analysis_url": "https://api.spotify.com/v1/audio-analysis/62vpWI1CHwFy7tMIcSStl8", "duration_ms": 292987, "speechiness": 0.332, "energy": 0.521, "loudness": -8.465, "track_href": "https://api.spotify.com/v1/tracks/62vpWI1CHwFy7tMIcSStl8", "id": "62vpWI1CHwFy7tMIcSStl8", "time_signature": 4, "mode": 0, "danceability": 0.696, "uri": "spotify:track:62vpWI1CHwFy7tMIcSStl8", "valence": 0.458, "instrumentalness": 0, "liveness": 0.0565, "tempo": 100.0, "key": 10, "type": "audio_features", "acousticness": 0.302}, {"analysis_url": "https://api.spotify.com/v1/audio-analysis/6Q2FftbUG530lCtBI74bMH", "duration_ms": 209269, "speechiness": 0.0568, "energy": 0.81, "loudness": -5.274, "track_href": "https://api.spotify.com/v1/tracks/6Q2FftbUG530lCtBI74bMH", "id": "6Q2FftbUG530lCtBI74bMH", "time_signature": 4, "mode": 0, "danceability": 0.839, "uri": "spotify:track:6Q2FftbUG530lCtBI74bMH", "valence": 0.814, "instrumentalness": 0, "liveness": 0.117, "tempo": 129.014, "key": 5, "type": "audio_features", "acousticness": 0.501}, {"analysis_url": "https://api.spotify.com/v1/audio-analysis/6SwRhMLwNqEi6alNPVG00n", "duration_ms": 227360, "speechiness": 0.055, "energy": 0.541, "loudness": -8.926, "track_href": "https://api.spotify.com/v1/tracks/6SwRhMLwNqEi6alNPVG00n", "id": "6SwRhMLwNqEi6alNPVG00n", "time_signature": 4, "mode": 0, "danceability": 0.681, "uri": "spotify:track:6SwRhMLwNqEi6alNPVG00n", "valence": 0.413, "instrumentalness": 0, "liveness": 0.167, "tempo": 110.803, "key": 9, "type": "audio_features", "acousticness": 0.0224}, {"analysis_url": "https://api.spotify.com/v1/audio-analysis/59J5nzL1KniFHnU120dQzt", "duration_ms": 235535, "speechiness": 0.254, "energy": 0.622, "loudness": -6.741, "track_href": "https://api.spotify.com/v1/tracks/59J5nzL1KniFHnU120dQzt", "id": "59J5nzL1KniFHnU120dQzt", "time_signature": 4, "mode": 1, "danceability": 0.785, "uri": "spotify:track:59J5nzL1KniFHnU120dQzt", "valence": 0.466, "instrumentalness": 0, "liveness": 0.154, "tempo": 78.475, "key": 8, "type": "audio_features", "acousticness": 0.0133}]