[{"analysis_url": "https://api.spotify.com/v1/audio-analysis/6WC5fhc9XMaCrUNKNjm9xE", "duration_ms": 216467, "speechiness": 0.057, "energy": 0.713, "loudness": -3.523, "track_href": "https://api.spotify.com/v1/tracks/6WC5fhc9XMaCrUNKNjm9xE", "id": "6WC5fhc9XMaCrUNKNjm9xE", "time_signature": 4, "mode": 1, "danceability": 0.718, "uri": "spotify:track:6WC5fhc9XMaCrUNKNjm9xE", "valence": 0.108, "instrumentalness": 0, "liveness": 0.0887, "tempo": 134.989, "key": 8, "type": "audio_features", "acousticness": 0.0262}, {"analysis_url": "https://api.spotify.com/v1/audio-analysis/1zWMf9bVyhY5W3ZORbjNWt", "duration_ms": 192133, "speechiness": 0.114, "energy": 0.832, "loudness": -5.732, "track_href": "https://api.spotify.com/v1/tracks/1zWMf9bVyhY5W3ZORbjNWt", "id": "1zWMf9bVyhY5W3ZORbjNWt", "time_signature": 4, "mode": 0, "danceability": 0.565, "uri": "spotify:track:1zWMf9bVyhY5W3ZORbjNWt", "valence": 0.233, "instrumentalness": 0, "liveness": 0.26, "tempo": 112.827, "key": 10, "type": "audio_features", "acousticness": 0.0247}, {"analysis_url": "https://api.spotify.com/v1/audio-analysis/2zRiYzBzeabQQ16BK3c6jk", "duration_ms": 207174, "speechiness": 0.168, "energy": 0.873, "loudness": -3.825, "track_href": "https://api.spotify.com/v1/tracks/2zRiYzBzeabQQ16BK3c6jk", "id": "2zRiYzBzeabQQ16BK3c6jk", "time_signature": 4, "mode": 0, "danceability": 0.534, "uri": "spotify:track:2zRiYzBzeabQQ16BK3c6jk", "valence": 0.483, "instrumentalness": 0, "liveness": 0.062, "tempo": 117.803, "key": 1, "type": "audio_features", "acousticness": 0.0815}, {"analysis_url": "https://api.spotify.com/v1/audio-analysis/0z9UVN8VBHJ9HdfYsOuuNf", "duration_ms": 240067, "speechiness": 0.0277, "energy": 0.3, "loudness": -10.737, "track_href": "https://api.spotify.com/v1/tracks/0z9UVN8VBHJ9HdfYsOuuNf", "id": "0z9UVN8VBHJ9HdfYsOuuNf", "time_signature": 4, "mode": 1, "danceability": 0.476, "uri": "spotify:track:0z9UVN8VBHJ9HdfYsOuuNf", "valence": 0.304, "instrumentalness": 1.53e-05, "liveness": 0.0732, "tempo": 144.163, "key": 7, "type": "audio_features", "acousticness": 0.893}, {"analysis_url": "https://api.spotify.com/v1/audio-analysis/3yWsWi2PAo9s6elIhnywIS", "duration_ms": 261372, "speechiness": 0.0357, "energy": 0.826, "loudness": -4.87, "track_href": "https://api.spotify.com/v1/tracks/3yWsWi2PAo9s6elIhnywIS", "id": "3yWsWi2PAo9s6elIhnywIS", "time_signature": 4, "mode": 1, "danceability": 0.581, "uri": "spotify:track:3yWsWi2PAo9s6elIhnywIS", "valence": 0.492, "instrumentalness": 1.56e-06, "liveness": 0.792, "tempo": 100.018, "key": 0, "type": "audio_features", "acousticness": 0.00773}, {"analysis_url": "https://api.spotify.com/v1/audio-analysis/4CGGIk81BvfCZiscwFP6t0", "duration_ms": 228361, "speechiness": 0.202, "energy": 0.692, "loudness": -5.836, "track_href": "https://api.spotify.com/v1/tracks/4CGGIk81BvfCZiscwFP6t0", "id": "4CGGIk81BvfCZiscwFP6t0", "time_signature": 4, "mode": 1, "danceability": 0.503, "uri": "spotify:track:4CGGIk81BvfCZiscwFP6t0", "valence": 0.208, "instrumentalness": 0, "liveness": 0.133, "tempo": 102.604, "key": 0, "type": "audio_features", "acousticness": 0.00453}, {"analysis_url": "https://api.spotify.com/v1/audio-analysis/360Wr96ywrCQq4kTAJ8Pq6", "duration_ms": 220013, "speechiness": 0.0306, "energy": 0.593, "loudness": -6.024, "track_href": "https://api.spotify.com/v1/tracks/360Wr96ywrCQq4kTAJ8Pq6", "id": "360Wr96ywrCQq4kTAJ8Pq6", "time_signature": 4, "mode": 0, "danceability": 0.576, "uri": "spotify:track:360Wr96ywrCQq4kTAJ8Pq6", "valence": 0.373, "instrumentalness": 0.000767, "liveness": 0.237, "tempo": 157.993, "key": 9, "type": "audio_features", "acousticness": 0.0467}, {"analysis_url": "https://api.spotify.com/v1/audio-analysis/4fINc8dnfcz7AdhFYVA4i7", "duration_ms": 192200, "speechiness": 0.0605, "energy": 0.718, "loudness": -4.736, "track_href": "https://api.spotify.com/v1/tracks/4fINc8dnfcz7AdhFYVA4i7", "id": "4fINc8dnfcz7AdhFYVA4i7", "time_signature": 4, "mode": 0, "danceability": 0.668, "uri": "spotify:track:4fINc8dnfcz7AdhFYVA4i7", "valence": 0.345, "instrumentalness": 0, "liveness": 0.104, "tempo": 91.993, "key": 1, "type": "audio_features", "acousticness": 0.0165}, {"analysis_url": "https://api.spotify.com/v1/audio-analysis/7a86XRg84qjasly9f6bPSD", "duration_ms": 250627, "speechiness": 0.075, "energy": 0.638, "loudness": -5.576, "track_href": "https://api.spotify.com/v1/tracks/7a86XRg84qjasly9f6bPSD", "id": "7a86XRg84qjasly9f6bPSD", "time_signature": 4, "mode": 1, "danceability": 0.378, "uri": "spotify:track:7a86XRg84qjasly9f6bPSD", "valence": 0.735, "instrumentalness": 7.66e-05, "liveness": 0.0849, "tempo": 184.086, "key": 10, "type": "audio_features", "acousticness": 0.02}, {"analysis_url": "https://api.spotify.com/v1/audio-analysis/1ehPJRt49h6N0LoryqKZXq", "duration_ms": 175507, "speechiness": 0.395, "energy": 0.562, "loudness": -9.609, "track_href": "https://api.spotify.com/v1/tracks/1ehPJRt49h6N0LoryqKZXq", "id": "1ehPJRt49h6N0LoryqKZXq", "time_signature": 4, "mode": 1, "danceability": 0.317, "uri": "spotify:track:1ehPJRt49h6N0LoryqKZXq", "valence": 0.132, "instrumentalness": 0.000144, "liveness": 0.0667, "tempo": 181.1, "key": 9, "type": "audio_features", "acousticness": 0.124}, {"analysis_url": "https://api.spotify.com/v1/audio-analysis/04CttTezSnv71USiiG9mIo", "duration_ms": 218447, "speechiness": 0.0362, "energy": 0.662, "loudness": -6.858, "track_href": "https://api.spotify.com/v1/tracks/04CttTezSnv71USiiG9mIo", "id": "04CttTezSnv71USiiG9mIo", "time_signature": 4, "mode": 0, "danceability": 0.595, "uri": "spotify:track:04CttTezSnv71USiiG9mIo", "valence": 0.417, "instrumentalness": 0, "liveness": 0.0804, "tempo": 96.053, "key": 11, "type": "audio_features", "acousticness": 0.0178}, {"analysis_url": "https://api.spotify.com/v1/audio-analysis/2XRCxFtPqSsnY94jZCFuYu", "duration_ms": 283467, "speechiness": 0.0509, "energy": 0.673, "loudness": -5.506, "track_href": "https://api.spotify.com/v1/tracks/2XRCxFtPqSsnY94jZCFuYu", "id": "2XRCxFtPqSsnY94jZCFuYu", "time_signature": 5, "mode": 1, "danceability": 0.399, "uri": "spotify:track:2XRCxFtPqSsnY94jZCFuYu", "valence": 0.285, "instrumentalness": 2.44e-05, "liveness": 0.118, "tempo": 142.255, "key": 0, "type": "audio_features", "acousticness": 0.584}, {"analysis_url": "https://api.spotify.com/v1/audio-analysis/5Lbsc65org0b85kNsPkluY", "duration_ms": 291080, "speechiness": 0.0397, "energy": 0.842, "loudness": -4.113, "track_href": "https://api.spotify.com/v1/tracks/5Lbsc65org0b85kNsPkluY", "id": "5Lbsc65org0b85kNsPkluY", "time_signature": 4, "mode": 1, "danceability": 0.554, "uri": "spotify:track:5Lbsc65org0b85kNsPkluY", "valence": 0.348, "instrumentalness": 0, "liveness": 0.106, "tempo": 114.036, "key": 5, "type": "audio_features", "acousticness": 0.287}, {"analysis_url": "https://api.spotify.com/v1/audio-analysis/7brQHA2CgQpcMBiOlfiXYb", "duration_ms": 251187, "speechiness": 0.0411, "energy": 0.701, "loudness": -5.693, "track_href": "https://api.spotify.com/v1/tracks/7brQHA2CgQpcMBiOlfiXYb", "id": "7brQHA2CgQpcMBiOlfiXYb", "time_signature": 4, "mode": 0, "danceability": 0.464, "uri": "spotify:track:7brQHA2CgQpcMBiOlfiXYb", "valence": 0.356, "instrumentalness": 0.309, "liveness": 0.335, "tempo": 83.996, "key": 6, "type": "audio_features", "acousticness": 0.00892}, {"analysis_url": "https://api.spotify.com/v1/audio-analysis/6mz1fBdKATx6qP4oP1I65G", "duration_ms": 251733, "speechiness": 0.086, "energy": 0.605, "loudness": -9.359, "track_href": "https://api.spotify.com/v1/tracks/6mz1fBdKATx6qP4oP1I65G", "id": "6mz1fBdKATx6qP4oP1I65G", "time_signature": 4, "mode": 0, "danceability": 0.749, "uri": "spotify:track:6mz1fBdKATx6qP4oP1I65G", "valence": 0.966, "instrumentalness": 0.0381, "liveness": 0.115, "tempo": 142.024, "key": 8, "type": "audio_features", "acousticness": 0.00186}, {"analysis_url": "https://api.spotify.com/v1/audio-analysis/5XiZK7m9PLppgIzJBpw2x5", "duration_ms": 165084, "speechiness": 0.0617, "energy": 0.664, "loudness": -4.768, "track_href": "https://api.spotify.com/v1/tracks/5XiZK7m9PLppgIzJBpw2x5", "id": "5XiZK7m9PLppgIzJBpw2x5", "time_signature": 4, "mode": 0, "danceability": 0.649, "uri": "spotify:track:5XiZK7m9PLppgIzJBpw2x5", "valence": 0.339, "instrumentalness": 0, "liveness": 0.15, "tempo": 110.041, "key": 8, "type": "audio_features", "acousticness": 0.178}, {"analysis_url": "https://api.spotify.com/v1/audio-analysis/0BCPKOYdS2jbQ8iyB56Zns", "duration_ms": 307880, "speechiness": 0.0279, "energy": 0.749, "loudness": -7.215, "track_href": "https://api.spotify.com/v1/tracks/0BCPKOYdS2jbQ8iyB56Zns", "id": "0BCPKOYdS2jbQ8iyB56Zns", "time_signature": 4, "mode": 0, "danceability": 0.577, "uri": "spotify:track:0BCPKOYdS2jbQ8iyB56Zns", "valence": 0.261, "instrumentalness": 0.0112, "liveness": 0.183, "tempo": 130.969, "key": 5, "type": "audio_features", "acousticness": 0.599}, {"analysis_url": "https://api.spotify.com/v1/audio-analysis/3GZD6HmiNUhxXYf8Gch723", "duration_ms": 234093, "speechiness": 0.236, "energy": 0.596, "loudness": -4.957, "track_href": "https://api.spotify.com/v1/tracks/3GZD6HmiNUhxXYf8Gch723", "id": "3GZD6HmiNUhxXYf8Gch723", "time_signature": 4, "mode": 0, "danceability": 0.907, "uri": "spotify:track:3GZD6HmiNUhxXYf8Gch723", "valence": 0.492, "instrumentalness": 0.000193, "liveness": 0.19, "tempo": 123.045, "key": 10, "type": "audio_features", "acousticness": 0.0284}, {"analysis_url": "https://api.spotify.com/v1/audio-analysis/6vzR3sLeGKyEILZq5Top3r", "duration_ms": 197720, "speechiness": 0.0478, "energy": 0.435, "loudness": -6.389, "track_href": "https://api.spotify.com/v1/tracks/6vzR3sLeGKyEILZq5Top3r", "id": "6vzR3sLeGKyEILZq5Top3r", "time_signature": 3, "mode": 0, "danceability": 0.583, "uri": "spotify:track:6vzR3sLeGKyEILZq5Top3r", "valence": 0.129, "instrumentalness": 0, "liveness": 0.0763, "tempo": 128.035, "key": 5, "type": "audio_features", "acousticness": 0.0978}, {"analysis_url": "https://api.spotify.com/v1/audio-analysis/57kR5SniQIbsbVoIjjOUDa", "duration_ms": 247267, "speechiness": 0.196, "energy": 0.722, "loudness": -5.369, "track_href": "https://api.spotify.com/v1/tracks/57kR5SniQIbsbVoIjjOUDa", "id": "57kR5SniQIbsbVoIjjOUDa", "time_signature": 4, "mode": 0, "danceability": 0.426, "uri": "spotify:track:57kR5SniQIbsbVoIjjOUDa", "valence": 0.25, "instrumentalness": 1.27e-06, "liveness": 0.262, "tempo": 196.133, "key": 5, "type": "audio_features", "acousticness": 0.0113}]