[{"analysis_url": "https://api.spotify.com/v1/audio-analysis/1vvNmPOiUuyCbgWmtc6yfm", "duration_ms": 219160, "speechiness": 0.0427, "energy": 0.913, "loudness": -3.059, "track_href": "https://api.spotify.com/v1/tracks/1vvNmPOiUuyCbgWmtc6yfm", "id": "1vvNmPOiUuyCbgWmtc6yfm", "time_signature": 4, "mode": 0, "danceability": 0.819, "uri": "spotify:track:1vvNmPOiUuyCbgWmtc6yfm", "valence": 0.536, "instrumentalness": 3.72e-05, "liveness": 0.161, "tempo": 119.989, "key": 4, "type": "audio_features", "acousticness": 0.0935}, {"analysis_url": "https://api.spotify.com/v1/audio-analysis/0ua0Go4NN4Td7l0Zre6Ce3", "duration_ms": 237507, "speechiness": 0.0486, "energy": 0.649, "loudness": -7.505, "track_href": "https://api.spotify.com/v1/tracks/0ua0Go4NN4Td7l0Zre6Ce3", "id": "0ua0Go4NN4Td7l0Zre6Ce3", "time_signature": 4, "mode": 0, "danceability": 0.634, "uri": "spotify:track:0ua0Go4NN4Td7l0Zre6Ce3", "valence": 0.509, "instrumentalness": 0, "liveness": 0.482, "tempo": 90.482, "key": 6, "type": "audio_features", "acousticness": 0.0315}, {"analysis_url": "https://api.spotify.com/v1/audio-analysis/5gWtkdgdyt5bZt9i6n3Kqd", "duration_ms": 201520, "speechiness": 0.0589, "energy": 0.692, "loudness": -4.513, "track_href": "https://api.spotify.com/v1/tracks/5gWtkdgdyt5bZt9i6n3Kqd", "id": "5gWtkdgdyt5bZt9i6n3Kqd", "time_signature": 4, "mode": 1, "danceability": 0.568, "uri": "spotify:track:5gWtkdgdyt5bZt9i6n3Kqd", "valence": 0.577, "instrumentalness": 0, "liveness": 0.148, "tempo": 92.023, "key": 8, "type": "audio_features", "acousticness": 0.0161}, {"analysis_url": "https://api.spotify.com/v1/audio-analysis/74vs7PD7iG2GnWUGnb8Yuq", "duration_ms": 174600, "speechiness": 0.0564, "energy": 0.747, "loudness": -4.315, "track_href": "https://api.spotify.com/v1/tracks/74vs7PD7iG2GnWUGnb8Yuq", "id": "74vs7PD7iG2GnWUGnb8Yuq", "time_signature": 4, "mode": 0, "danceability": 0.589, "uri": "spotify:track:74vs7PD7iG2GnWUGnb8Yuq", "valence": 0.424, "instrumentalness": 0, "liveness": 0.0817, "tempo": 130.129, "key": 11, "type": "audio_features", "acousticness": 0.0041}, {"analysis_url": "https://api.spotify.com/v1/audio-analysis/2kJqNHHGOzLNahukdvlDWN", "duration_ms": 196466, "speechiness": 0.0987, "energy": 0.447, "loudness": -8.315, "track_href": "https://api.spotify.com/v1/tracks/2kJqNHHGOzLNahukdvlDWN", "id": "2kJqNHHGOzLNahukdvlDWN", "time_signature": 4, "mode": 1, "danceability": 0.658, "uri": "spotify:track:2kJqNHHGOzLNahukdvlDWN", "valence": 0.397, "instrumentalness": 3.67e-06, "liveness": 0.0828, "tempo": 141.742, "key": 9, "type": "audio_features", "acousticness": 0.755}, {"analysis_url": "https://api.spotify.com/v1/audio-analysis/1D066zixBwqFYqBhKgdPzp", "duration_ms": 292373, "speechiness": 0.337, "energy": 0.598, "loudness": -7.651, "track_href": "https://api.spotify.com/v1/tracks/1D066zixBwqFYqBhKgdPzp", "id": "1D066zixBwqFYqBhKgdPzp", "time_signature": 4, "mode": 0, "danceability": 0.904, "uri": "spotify:track:1D066zixBwqFYqBhKgdPzp", "valence": 0.785, "instrumentalness": 0, "liveness": 0.111, "tempo": 129.055, "key": 8, "type": "audio_features", "acousticness": 0.0568}, {"analysis_url": "https://api.spotify.com/v1/audio-analysis/4ToeppjiHi7kGMAVUvosv0", "duration_ms": 230933, "speechiness": 0.0655, "energy": 0.56, "loudness": -6.849, "track_href": "https://api.spotify.com/v1/tracks/4ToeppjiHi7kGMAVUvosv0", "id": "4ToeppjiHi7kGMAVUvosv0", "time_signature": 4, "mode": 1, "danceability": 0.702, "uri": "spotify:track:4ToeppjiHi7kGMAVUvosv0", "valence": 0.45, "instrumentalness": 0, "liveness": 0.098, "tempo": 102.976, "key": 10, "type": "audio_features", "acousticness": 0.0169}, {"analysis_url": "https://api.spotify.com/v1/audio-analysis/7iCeaYJSEdGWeFNTAEqUzJ", "duration_ms": 212747, "speechiness": 0.0362, "energy": 0.475, "loudness": -8.642, "track_href": "https://api.spotify.com/v1/tracks/7iCeaYJSEdGWeFNTAEqUzJ", "id": "7iCeaYJSEdGWeFNTAEqUzJ", "time_signature": 4, "mode": 0, "danceability": 0.614, "uri": "spotify:track:7iCeaYJSEdGWeFNTAEqUzJ", "valence": 0.422, "instrumentalness": 1.06e-06, "liveness": 0.265, "tempo": 99.968, "key": 7, "type": "audio_features", "acousticness": 0.395}, {"analysis_url": "https://api.spotify.com/v1/audio-analysis/4RnCPWlBsY7oUDdyruod7Y", "duration_ms": 200093, "speechiness": 0.0696, "energy": 0.652, "loudness": -9.101, "track_href": "https://api.spotify.com/v1/tracks/4RnCPWlBsY7oUDdyruod7Y", "id": "4RnCPWlBsY7oUDdyruod7Y", "time_signature": 4, "mode": 1, "danceability": 0.733, "uri": "spotify:track:4RnCPWlBsY7oUDdyruod7Y", "valence": 0.459, "instrumentalness": 2.37e-06, "liveness": 0.521, "tempo": 99.998, "key": 7, "type": "audio_features", "acousticness": 0.419}, {"analysis_url": "https://api.spotify.com/v1/audio-analysis/1vrd6UOGamcKNGnSHJQlSt", "duration_ms": 235267, "speechiness": 0.0302, "energy": 0.721, "loudness": -3.913, "track_href": "https://api.spotify.com/v1/tracks/1vrd6UOGamcKNGnSHJQlSt", "id": "1vrd6UOGamcKNGnSHJQlSt", "time_signature": 4, "mode": 1, "danceability": 0.615, "uri": "spotify:track:1vrd6UOGamcKNGnSHJQlSt", "valence": 0.324, "instrumentalness": 0, "liveness": 0.0925, "tempo": 119.007, "key": 2, "type": "audio_features", "acousticness": 0.151}, {"analysis_url": "https://api.spotify.com/v1/audio-analysis/33bURv895AN4FkBvgFo2dx", "duration_ms": 278800, "speechiness": 0.0335, "energy": 0.647, "loudness": -4.68, "track_href": "https://api.spotify.com/v1/tracks/33bURv895AN4FkBvgFo2dx", "id": "33bURv895AN4FkBvgFo2dx", "time_signature": 4, "mode": 0, "danceability": 0.624, "uri": "spotify:track:33bURv895AN4FkBvgFo2dx", "valence": 0.379, "instrumentalness": 0.0038, "liveness": 0.221, "tempo": 136.022, "key": 3, "type": "audio_features", "acousticness": 0.0169}, {"analysis_url": "https://api.spotify.com/v1/audio-analysis/1NkwZ9TnIs8js6G0M6M7RU", "duration_ms": 202480, "speechiness": 0.0406, "energy": 0.734, "loudness": -5.814, "track_href": "https://api.spotify.com/v1/tracks/1NkwZ9TnIs8js6G0M6M7RU", "id": "1NkwZ9TnIs8js6G0M6M7RU", "time_signature": 4, "mode": 1, "danceability": 0.774, "uri": "spotify:track:1NkwZ9TnIs8js6G0M6M7RU", "valence": 0.839, "instrumentalness": 0, "liveness": 0.0659, "tempo": 120.075, "key": 7, "type": "audio_features", "acousticness": 0.0476}, {"analysis_url": "https://api.spotify.com/v1/audio-analysis/3Dkvp3L4w0uJFYfIPa8E9H", "duration_ms": 244820, "speechiness": 0.0962, "energy": 0.401, "loudness": -8.241, "track_href": "https://api.spotify.com/v1/tracks/3Dkvp3L4w0uJFYfIPa8E9H", "id": "3Dkvp3L4w0uJFYfIPa8E9H", "time_signature": 4, "mode": 1, "danceability": 0.494, "uri": "spotify:track:3Dkvp3L4w0uJFYfIPa8E9H", "valence": 0.155, "instrumentalness": 0.000283, "liveness": 0.11, "tempo": 83.246, "key": 5, "type": "audio_features", "acousticness": 0.552}, {"analysis_url": "https://api.spotify.com/v1/audio-analysis/7xapw9Oy21WpfEcib2ErSA", "duration_ms": 182947, "speechiness": 0.05, "energy": 0.565, "loudness": -9.124, "track_href": "https://api.spotify.com/v1/tracks/7xapw9Oy21WpfEcib2ErSA", "id": "7xapw9Oy21WpfEcib2ErSA", "time_signature": 4, "mode": 0, "danceability": 0.672, "uri": "spotify:track:7xapw9Oy21WpfEcib2ErSA", "valence": 0.844, "instrumentalness": 0, "liveness": 0.0895, "tempo": 161.955, "key": 6, "type": "audio_features", "acousticness": 0.527}, {"analysis_url": "https://api.spotify.com/v1/audio-analysis/5ArQzSBevAdXTxRY6Ulhbq", "duration_ms": 206903, "speechiness": 0.0703, "energy": 0.799, "loudness": -4.564, "track_href": "https://api.spotify.com/v1/tracks/5ArQzSBevAdXTxRY6Ulhbq", "id": "5ArQzSBevAdXTxRY6Ulhbq", "time_signature": 4, "mode": 0, "danceability": 0.712, "uri": "spotify:track:5ArQzSBevAdXTxRY6Ulhbq", "valence": 0.591, "instrumentalness": 6.4e-05, "liveness": 0.37, "tempo": 83.996, "key": 7, "type": "audio_features", "acousticness": 0.0447}, {"analysis_url": "https://api.spotify.com/v1/audio-analysis/6JsfvqClYnc2R5yZ67C2ch", "duration_ms": 217793, "speechiness": 0.045, "energy": 0.805, "loudness": -5.188, "track_href": "https://api.spotify.com/v1/tracks/6JsfvqClYnc2R5yZ67C2ch", "id": "6JsfvqClYnc2R5yZ67C2ch", "time_signature": 4, "mode": 1, "danceability": 0.632, "uri": "spotify:track:6JsfvqClYnc2R5yZ67C2ch", "valence": 0.429, "instrumentalness": 5.83e-05, "liveness": 0.161, "tempo": 93.009, "key": 0, "type": "audio_features", "acousticness": 0.0646}, {"analysis_url": "https://api.spotify.com/v1/audio-analysis/6pTDPaMcN5KSYD8hJ1uWId", "duration_ms": 233393, "speechiness": 0.0522, "energy": 0.533, "loudness": -6.426, "track_href": "https://api.spotify.com/v1/tracks/6pTDPaMcN5KSYD8hJ1uWId", "id": "6pTDPaMcN5KSYD8hJ1uWId", "time_signature": 4, "mode": 1, "danceability": 0.606, "uri": "spotify:track:6pTDPaMcN5KSYD8hJ1uWId", "valence": 0.221, "instrumentalness": 0, "liveness": 0.172, "tempo": 120.049, "key": 9, "type": "audio_features", "acousticness": 0.0424}, {"analysis_url": "https://api.spotify.com/v1/audio-analysis/0xLCa6dp0wmDUhkDGKzDpv", "duration_ms": 202400, "speechiness": 0.148, "energy": 0.688, "loudness": -5.515, "track_href": "https://api.spotify.com/v1/tracks/0xLCa6dp0wmDUhkDGKzDpv", "id": "0xLCa6dp0wmDUhkDGKzDpv", "time_signature": 4, "mode": 1, "danceability": 0.771, "uri": "spotify:track:0xLCa6dp0wmDUhkDGKzDpv", "valence": 0.307, "instrumentalness": 0, "liveness": 0.0578, "tempo": 92.003, "key": 7, "type": "audio_features", "acousticness": 0.00954}, {"analysis_url": "https://api.spotify.com/v1/audio-analysis/12lZTPlXwUtrQuhEty6098", "duration_ms": 203333, "speechiness": 0.0897, "energy": 0.695, "loudness": -4.973, "track_href": "https://api.spotify.com/v1/tracks/12lZTPlXwUtrQuhEty6098", "id": "12lZTPlXwUtrQuhEty6098", "time_signature": 4, "mode": 1, "danceability": 0.7, "uri": "spotify:track:12lZTPlXwUtrQuhEty6098", "valence": 0.633, "instrumentalness": 0, "liveness": 0.0319, "tempo": 122.028, "key": 7, "type": "audio_features", "acousticness": 0.00629}, {"analysis_url": "https://api.spotify.com/v1/audio-analysis/5E30LdtzQTGqRvNd7l6kG5", "duration_ms": 260173, "speechiness": 0.0329, "energy": 0.521, "loudness": -9.461, "track_href": "https://api.spotify.com/v1/tracks/5E30LdtzQTGqRvNd7l6kG5", "id": "5E30LdtzQTGqRvNd7l6kG5", "time_signature": 4, "mode": 1, "danceability": 0.588, "uri": "spotify:track:5E30LdtzQTGqRvNd7l6kG5", "valence": 0.337, "instrumentalness": 0.149, "liveness": 0.123, "tempo": 85.012, "key": 10, "type": "audio_features", "acousticness": 0.0678}]